[
  {
    "symbolicName": "jre",
    "version": {
      "major": 1,
      "minor": 0,
      "micro": 0,
      "qualifier": ""
    },
    "jarFileFingerprint": "be4124ecceb37230419f0f31ea6e7d50babb4973",
    "jarFileModificationDate": "2014-06-13T11:14:24.542-04:00",
    "location": "C:\\Program Files (x86)\\Java\\jre7\\lib\\jce.jar",
    "javaRuntime": true
  },
  {
    "symbolicName": "jre",
    "version": {
      "major": 1,
      "minor": 0,
      "micro": 0,
      "qualifier": ""
    },
    "jarFileFingerprint": "e17e67469925bd13731ae5e07dca651f97c8673f",
    "jarFileModificationDate": "2014-06-13T11:14:23.824-04:00",
    "location": "C:\\Program Files (x86)\\Java\\jre7\\lib\\ext\\dnsns.jar",
    "javaRuntime": true
  },
  {
    "symbolicName": "jre",
    "version": {
      "major": 1,
      "minor": 0,
      "micro": 0,
      "qualifier": ""
    },
    "jarFileFingerprint": "93e338c152d84859187ed038d52e1078502caa4a",
    "jarFileModificationDate": "2014-06-13T11:14:30.230-04:00",
    "location": "C:\\Program Files (x86)\\Java\\jre7\\lib\\ext\\localedata.jar",
    "javaRuntime": true
  },
  {
    "symbolicName": "jre",
    "version": {
      "major": 1,
      "minor": 0,
      "micro": 0,
      "qualifier": ""
    },
    "jarFileFingerprint": "17d71c8d24e8bb670c324969ff0ac13bb7952dea",
    "jarFileModificationDate": "2014-06-13T11:14:24.636-04:00",
    "location": "C:\\Program Files (x86)\\Java\\jre7\\lib\\resources.jar",
    "javaRuntime": true
  },
  {
    "symbolicName": "jre",
    "version": {
      "major": 1,
      "minor": 0,
      "micro": 0,
      "qualifier": ""
    },
    "jarFileFingerprint": "b7d6a1dbcc456bfdd24a0795856c972415730edd",
    "jarFileModificationDate": "2014-06-13T11:14:30.167-04:00",
    "location": "C:\\Program Files (x86)\\Java\\jre7\\lib\\jsse.jar",
    "javaRuntime": true
  },
  {
    "symbolicName": "jre",
    "version": {
      "major": 1,
      "minor": 0,
      "micro": 0,
      "qualifier": ""
    },
    "jarFileFingerprint": "d1c518045fddc9c9bef3d3cee1b37e5d6d3559f1",
    "jarFileModificationDate": "2014-06-13T11:14:24.152-04:00",
    "location": "C:\\Program Files (x86)\\Java\\jre7\\lib\\ext\\zipfs.jar",
    "javaRuntime": true
  },
  {
    "symbolicName": "jre",
    "version": {
      "major": 1,
      "minor": 0,
      "micro": 0,
      "qualifier": ""
    },
    "jarFileFingerprint": "95dc9053062d68cde4e8c38494cc63aefd7b0a42",
    "jarFileModificationDate": "2014-06-13T11:14:24.089-04:00",
    "location": "C:\\Program Files (x86)\\Java\\jre7\\lib\\ext\\sunec.jar",
    "javaRuntime": true
  },
  {
    "symbolicName": "jre",
    "version": {
      "major": 1,
      "minor": 0,
      "micro": 0,
      "qualifier": ""
    },
    "jarFileFingerprint": "05000691a551f1434276c9ae892f6bc08de48698",
    "jarFileModificationDate": "2014-06-13T11:14:29.652-04:00",
    "location": "C:\\Program Files (x86)\\Java\\jre7\\lib\\rt.jar",
    "javaRuntime": true
  },
  {
    "symbolicName": "jre",
    "version": {
      "major": 1,
      "minor": 0,
      "micro": 0,
      "qualifier": ""
    },
    "jarFileFingerprint": "a52c950086f08535a673cece268c8ee69c446cea",
    "jarFileModificationDate": "2014-06-13T11:14:23.792-04:00",
    "location": "C:\\Program Files (x86)\\Java\\jre7\\lib\\ext\\access-bridge-32.jar",
    "javaRuntime": true
  },
  {
    "symbolicName": "jre",
    "version": {
      "major": 1,
      "minor": 0,
      "micro": 0,
      "qualifier": ""
    },
    "jarFileFingerprint": "0101778298b22813445708274539ae6adb8df97a",
    "jarFileModificationDate": "2014-06-13T11:14:29.761-04:00",
    "location": "C:\\Program Files (x86)\\Java\\jre7\\lib\\charsets.jar",
    "javaRuntime": true
  },
  {
    "symbolicName": "jre",
    "version": {
      "major": 1,
      "minor": 0,
      "micro": 0,
      "qualifier": ""
    },
    "jarFileFingerprint": "94b8814896e82ab967e00cae65e41a7d9eceb98d",
    "jarFileModificationDate": "2014-06-13T11:14:24.542-04:00",
    "location": "C:\\Program Files (x86)\\Java\\jre7\\lib\\jfr.jar",
    "javaRuntime": true
  },
  {
    "symbolicName": "jre",
    "version": {
      "major": 1,
      "minor": 0,
      "micro": 0,
      "qualifier": ""
    },
    "jarFileFingerprint": "1826204b0e05aef412b595321866f7d190e0498d",
    "jarFileModificationDate": "2014-06-13T11:14:24.089-04:00",
    "location": "C:\\Program Files (x86)\\Java\\jre7\\lib\\ext\\sunjce_provider.jar",
    "javaRuntime": true
  },
  {
    "symbolicName": "org.xerial.sqlite-jdbc4",
    "version": {
      "major": 3,
      "minor": 8,
      "micro": 2,
      "qualifier": "SNAPSHOT"
    },
    "jarFileFingerprint": "7cd00f5b72f6ee56b25ff73d3f677223cca0cfe4",
    "jarFileModificationDate": "2014-06-19T11:44:02.886-04:00",
    "location": "C:\\Users\\mbell_000\\Documents\\GitHub\\GlassScriptManagementPS\\GlassScriptManagement\\src\\sqlite-jdbc4-3.8.2-SNAPSHOT.jar",
    "javaRuntime": false
  },
  {
    "symbolicName": "jre",
    "version": {
      "major": 1,
      "minor": 0,
      "micro": 0,
      "qualifier": ""
    },
    "jarFileFingerprint": "5e51ce82a095b4a23291b1cd35e6f1488efc5776",
    "jarFileModificationDate": "2014-06-13T11:14:24.152-04:00",
    "location": "C:\\Program Files (x86)\\Java\\jre7\\lib\\ext\\sunpkcs11.jar",
    "javaRuntime": true
  },
  {
    "symbolicName": "jre",
    "version": {
      "major": 1,
      "minor": 0,
      "micro": 0,
      "qualifier": ""
    },
    "jarFileFingerprint": "a3d1a9689f1c8e36ab64fb669df92076771c42f2",
    "jarFileModificationDate": "2014-06-13T11:14:24.136-04:00",
    "location": "C:\\Program Files (x86)\\Java\\jre7\\lib\\ext\\sunmscapi.jar",
    "javaRuntime": true
  },
  {
    "symbolicName": "jre",
    "version": {
      "major": 1,
      "minor": 0,
      "micro": 0,
      "qualifier": ""
    },
    "jarFileFingerprint": "b65b7abccac66f3f5a5c36cbff0f5b9961d2e1f8",
    "jarFileModificationDate": "2014-06-13T11:14:24.027-04:00",
    "location": "C:\\Program Files (x86)\\Java\\jre7\\lib\\ext\\jaccess.jar",
    "javaRuntime": true
  },
  {
    "symbolicName": "miglayout15-swing",
    "version": {
      "major": -1,
      "minor": -1,
      "micro": -1,
      "qualifier": ""
    },
    "jarFileFingerprint": "f00b72f394c1e22f6499b80f715272300da299ca",
    "jarFileModificationDate": "2014-06-19T13:13:31.571-04:00",
    "location": "C:\\Users\\mbell_000\\Documents\\GitHub\\GlassScriptManagementPS\\GlassScriptManagement\\miglayout15-swing.jar",
    "javaRuntime": false
  }
]